eezy_logging/__init__.py
eezy_logging/handler.py
eezy_logging/serializer.py
eezy_logging/worker.py
eezy_logging/queues/__init__.py
eezy_logging/queues/base.py
eezy_logging/queues/deque.py
eezy_logging/queues/memory.py
eezy_logging/queues/redis.py
eezy_logging/sinks/__init__.py
eezy_logging/sinks/base.py
eezy_logging/sinks/elasticsearch_sink.py
eezy_logging/sinks/opensearch_sink.py
eezy_logging/utils/__init__.py
eezy_logging-0.1.1.dist-info/METADATA
eezy_logging-0.1.1.dist-info/WHEEL
eezy_logging-0.1.1.dist-info/RECORD
