Metadata-Version: 2.4
Name: eezy-logging
Version: 0.1.1
Summary: A non-blocking, queue-based Python logging library for shipping logs to Elasticsearch and other destinations
Project-URL: Homepage, https://github.com/tintty1/eezy-logging
Project-URL: Repository, https://github.com/tintty1/eezy-logging
Project-URL: Documentation, https://github.com/tintty1/eezy-logging
License: MIT
Keywords: async,elasticsearch,logging,opensearch,queue
Classifier: Intended Audience :: Developers
Classifier: License :: OSI Approved :: MIT License
Classifier: Programming Language :: Python :: 3
Classifier: Programming Language :: Python :: 3.10
Classifier: Programming Language :: Python :: 3.11
Classifier: Programming Language :: Python :: 3.12
Classifier: Topic :: Software Development :: Libraries :: Python Modules
Requires-Python: >=3.10
Provides-Extra: elasticsearch
Requires-Dist: elasticsearch>=7.0; extra == 'elasticsearch'
Provides-Extra: opensearch
Requires-Dist: opensearch-py>=2.0; extra == 'opensearch'
Provides-Extra: redis
Requires-Dist: redis>=5.0; extra == 'redis'
